figurepage/__init__.py
figurepage/__main__.py
figurepage-0.1.0.dist-info/METADATA
figurepage-0.1.0.dist-info/WHEEL
figurepage-0.1.0.dist-info/entry_points.txt
figurepage-0.1.0.dist-info/top_level.txt
figurepage-0.1.0.dist-info/RECORD
