Metadata-Version: 2.1
Name: figurepage
Version: 0.1.0
Summary: Extensions to OpenSeesPy.
Home-page: https://github.com/otaithleigh/figurepage
Author: Peter Talley
Author-email: ptalley2@vols.utk.edu
License: UNKNOWN
Platform: UNKNOWN
Classifier: Programming Language :: Python :: 3
Classifier: Operating System :: OS Independent
Requires-Python: >=3.6
